ldkLibrary/__init__.py
ldkLibrary/annee_bissextile.py
ldkLibrary/table_multiplication.py
ldkLibrary-0.1.1.dist-info/METADATA
ldkLibrary-0.1.1.dist-info/WHEEL
ldkLibrary-0.1.1.dist-info/top_level.txt
ldkLibrary-0.1.1.dist-info/RECORD
